MANIFEST.in
README.md
requirements.txt
setup.cfg
setup.py
mldatautils/__init__.py
mldatautils/configs.py
mldatautils/conftest.py
mldatautils/db_utils.py
mldatautils/hyperdash_utils.py
mldatautils/logger.py
mldatautils/nlp_utils.py
mldatautils/s3_utils.py
mldatautils/utils.py
mldatautils.egg-info/PKG-INFO
mldatautils.egg-info/SOURCES.txt
mldatautils.egg-info/dependency_links.txt
mldatautils.egg-info/requires.txt
mldatautils.egg-info/top_level.txt