Metadata-Version: 1.1
Name: mldatautils
Version: 0.1.0
Summary: mldatautils
Home-page: https://github.com/chie8842/mldatautils
Author: Chie Hayashida
Author-email: chie8842@gmail.com
License: UNKNOWN
Download-URL: https://pypi.org/project/mldatautils
Platform: UNKNOWN
Classifier: Programming Language :: Python :: 3.5
Classifier: Programming Language :: Python :: 3.6
